webhook_utils/__init__.py
webhook_utils/contrib/__init__.py
webhook_utils/contrib/fastapi/__init__.py
webhook_utils/contrib/fastapi/webhook_router.py
webhook_utils/contrib/httpx_auth.py
webhook_utils/crypto/__init__.py
webhook_utils/crypto/_compare.py
webhook_utils/crypto/_generate.py
webhook_utils-0.3.2.dist-info/LICENSE
webhook_utils-0.3.2.dist-info/WHEEL
webhook_utils-0.3.2.dist-info/METADATA
webhook_utils-0.3.2.dist-info/RECORD
