Metadata-Version: 2.1
Name: webhook-utils
Version: 0.3.2
Summary: Short, well documented utilities for interacting with webhooks.
Home-page: https://github.com/tizz98/webhook-utils
License: MIT
Keywords: webhook,utils,utilities,webhooks
Author: Elijah Wilson
Author-email: dev.tizz98@gmail.com
Requires-Python: >=3.8,<4.0
Classifier: License :: OSI Approved :: MIT License
Classifier: Programming Language :: Python :: 3
Classifier: Programming Language :: Python :: 3.10
Classifier: Programming Language :: Python :: 3.8
Classifier: Programming Language :: Python :: 3.9
Provides-Extra: examples
Provides-Extra: fastapi
Provides-Extra: httpx
Requires-Dist: fastapi (>=0.70.1,<0.71.0); extra == "fastapi" or extra == "examples"
Requires-Dist: httpx (>=0.21.1,<0.22.0); extra == "httpx" or extra == "examples"
Requires-Dist: requests (>=2.26.0,<3.0.0); extra == "fastapi"
Requires-Dist: rich (>=10.16.1,<11.0.0); extra == "examples"
Requires-Dist: uvicorn[standard] (>=0.16.0,<0.17.0); extra == "examples"
Project-URL: Repository, https://github.com/tizz98/webhook-utils
